azure/mgmt/azurearcdata/__init__.py
azure/mgmt/azurearcdata/_azure_arc_data_management_client.py
azure/mgmt/azurearcdata/_configuration.py
azure/mgmt/azurearcdata/_version.py
azure/mgmt/azurearcdata/aio/__init__.py
azure/mgmt/azurearcdata/aio/_azure_arc_data_management_client.py
azure/mgmt/azurearcdata/aio/_configuration.py
azure/mgmt/azurearcdata/aio/operations/__init__.py
azure/mgmt/azurearcdata/aio/operations/_data_controllers_operations.py
azure/mgmt/azurearcdata/aio/operations/_operations.py
azure/mgmt/azurearcdata/aio/operations/_sql_managed_instances_operations.py
azure/mgmt/azurearcdata/aio/operations/_sql_server_instances_operations.py
azure/mgmt/azurearcdata/models/__init__.py
azure/mgmt/azurearcdata/models/_azure_arc_data_management_client_enums.py
azure/mgmt/azurearcdata/models/_models.py
azure/mgmt/azurearcdata/models/_models_py3.py
azure/mgmt/azurearcdata/operations/__init__.py
azure/mgmt/azurearcdata/operations/_data_controllers_operations.py
azure/mgmt/azurearcdata/operations/_operations.py
azure/mgmt/azurearcdata/operations/_sql_managed_instances_operations.py
azure/mgmt/azurearcdata/operations/_sql_server_instances_operations.py
azure_mgmt_azurearcdata-1.0.0.dist-info/METADATA
azure_mgmt_azurearcdata-1.0.0.dist-info/WHEEL
azure_mgmt_azurearcdata-1.0.0.dist-info/top_level.txt
azure_mgmt_azurearcdata-1.0.0.dist-info/RECORD
